krl_frameworks/__init__.py
krl_frameworks/__version__.py
krl_frameworks/py.typed
krl_frameworks/adapters/__init__.py
krl_frameworks/adapters/causal.py
krl_frameworks/adapters/connectors.py
krl_frameworks/adapters/network.py
krl_frameworks/adapters/spatial.py
krl_frameworks/core/__init__.py
krl_frameworks/core/base.py
krl_frameworks/core/bindings.py
krl_frameworks/core/capabilities.py
krl_frameworks/core/config.py
krl_frameworks/core/dashboard_spec.py
krl_frameworks/core/data_bundle.py
krl_frameworks/core/exceptions.py
krl_frameworks/core/execution_context.py
krl_frameworks/core/output_envelope.py
krl_frameworks/core/registry.py
krl_frameworks/core/state.py
krl_frameworks/core/tier.py
krl_frameworks/dag/__init__.py
krl_frameworks/dag/composer.py
krl_frameworks/governance/__init__.py
krl_frameworks/governance/audit.py
krl_frameworks/governance/binding_resolver.py
krl_frameworks/governance/ci_matrix.py
krl_frameworks/governance/closure_validator.py
krl_frameworks/governance/connector_registry.py
krl_frameworks/governance/package_resolver.py
krl_frameworks/governance/package_templates.py
krl_frameworks/governance/production_guard.py
krl_frameworks/indices/__init__.py
krl_frameworks/integration/__init__.py
krl_frameworks/layers/__init__.py
krl_frameworks/layers/arts_media/__init__.py
krl_frameworks/layers/arts_media/advanced.py
krl_frameworks/layers/arts_media/content_valuation.py
krl_frameworks/layers/arts_media/creative_economy.py
krl_frameworks/layers/arts_media/cultural_impact.py
krl_frameworks/layers/arts_media/ip_valuation.py
krl_frameworks/layers/arts_media/media_reach.py
krl_frameworks/layers/arts_media/platform_economics.py
krl_frameworks/layers/experimental/__init__.py
krl_frameworks/layers/experimental/advanced.py
krl_frameworks/layers/experimental/bayesian.py
krl_frameworks/layers/experimental/bunching.py
krl_frameworks/layers/experimental/did.py
krl_frameworks/layers/experimental/dml.py
krl_frameworks/layers/experimental/event_study.py
krl_frameworks-0.1.1.dist-info/METADATA
krl_frameworks-0.1.1.dist-info/WHEEL
krl_frameworks-0.1.1.dist-info/entry_points.txt
krl_frameworks-0.1.1.dist-info/top_level.txt
krl_frameworks-0.1.1.dist-info/RECORD
