Metadata-Version: 2.4
Name: krl-frameworks
Version: 0.1.1
Summary: Enterprise-grade meta-framework orchestration for socioeconomic analysis with deterministic CBSS pipelines
Author-email: Khipu Research Labs <engineering@krlabs.dev>
Maintainer-email: KRL Engineering <engineering@krlabs.dev>
License: Apache-2.0
Project-URL: Homepage, https://github.com/KR-Labs/krl-frameworks
Project-URL: Documentation, https://docs.krlabs.dev/frameworks
Project-URL: Repository, https://github.com/KR-Labs/krl-frameworks
Project-URL: Changelog, https://github.com/KR-Labs/krl-frameworks/blob/main/CHANGELOG.md
Keywords: socioeconomic-analysis,policy-evaluation,causal-inference,meta-framework,cbss,cohort-simulation,dag-orchestration,mpi,hdi,remsom
Classifier: Development Status :: 4 - Beta
Classifier: Intended Audience :: Science/Research
Classifier: Intended Audience :: Developers
Classifier: License :: OSI Approved :: Apache Software License
Classifier: Operating System :: OS Independent
Classifier: Programming Language :: Python :: 3
Classifier: Programming Language :: Python :: 3.11
Classifier: Programming Language :: Python :: 3.12
Classifier: Programming Language :: Python :: 3.13
Classifier: Topic :: Scientific/Engineering
Classifier: Topic :: Scientific/Engineering :: Information Analysis
Classifier: Typing :: Typed
Requires-Python: >=3.11
Requires-Dist: numpy>=1.26.0
Requires-Dist: pandas>=2.1.0
Requires-Dist: pydantic>=2.5.0
Requires-Dist: networkx>=3.2.0
Requires-Dist: krl-open-core>=0.2.0
Requires-Dist: krl-types~=0.2.0
Provides-Extra: dev
Requires-Dist: pytest>=7.0.0; extra == "dev"
Requires-Dist: pytest-cov>=4.0.0; extra == "dev"
Requires-Dist: pytest-asyncio>=0.21.0; extra == "dev"
Requires-Dist: ruff>=0.1.0; extra == "dev"
Requires-Dist: mypy>=1.0.0; extra == "dev"
Requires-Dist: pre-commit>=3.0.0; extra == "dev"
Provides-Extra: docs
Requires-Dist: sphinx>=7.0.0; extra == "docs"
Requires-Dist: sphinx-rtd-theme>=2.0.0; extra == "docs"
Requires-Dist: myst-parser>=2.0.0; extra == "docs"
Provides-Extra: causal
Requires-Dist: krl-causal-policy-toolkit>=1.0.0; extra == "causal"
Provides-Extra: geospatial
Requires-Dist: krl-geospatial-tools>=0.2.0; extra == "geospatial"
Provides-Extra: network
Requires-Dist: krl-network-analysis>=0.2.0; extra == "network"
Provides-Extra: connectors
Requires-Dist: krl-data-connectors>=1.0.0; extra == "connectors"
Provides-Extra: all
Requires-Dist: krl-frameworks[causal,connectors,dev,docs,geospatial,network]; extra == "all"
